ml_gan/__init__.py
ml_gan/text_reader.py
ml_gan/data/my_code.py
ml_gan-0.1.dist-info/METADATA
ml_gan-0.1.dist-info/WHEEL
ml_gan-0.1.dist-info/top_level.txt
ml_gan-0.1.dist-info/RECORD
