Metadata-Version: 2.1
Name: ml-gan
Version: 0.1
Summary: Code for GAN on Fashion MNIST dataset
Home-page: https://github.com/savioratharv/prac_testing
Author: davinci003
Author-email: freegpt00@gmail.com
